{"notes_02-more-basics.md":"fe116ad3","notes_01-getting-started.md":"f65a67a3","notes_03-output.md":"a0018379","notes_04-if-else.md":"f9106e28","index.md":"3336d2e8","notes_01-computers.md":"71521b7e","notes_01-start-programming.md":"0d8c480d","notes_02-simple-programs.md":"7432fbdb","notes_03-files.md":"90269632","notes_03-input-output.md":"8d633a78","notes_01-algorithms.md":"88f810b4","notes_04-logic.md":"4634a529","notes_03-input.md":"843f5ebc","notes_02-operators-and-types.md":"7c846eae","notes_04-prevent-errors.md":"60df5bd9","notes_04-switch.md":"8e3035e6","notes_06-functions-intro.md":"551e0975","notes_07-namespaces.md":"80a87e60","notes_08-2d-arrays.md":"3cdb14b6","notes_08-arrays-intro.md":"307a0df6","notes_08-arrays-strings.md":"1a5617bf","notes_08-enums-as-array-indexes.md":"281e7932","notes_08-ide.md":"dad4a057","notes_08-parallel-arrays.md":"94006efc","notes_08-search-and-sort.md":"c197854f","notes_09-structs-and-arrays.md":"5d2fc317","notes_09-structs-intro.md":"795d0d1d","notes_07-strings.md":"3c4da499","notes_06-scope-and-parameters.md":"1cfed40f","style-guide.md":"f93f9054","notes_06-static-variables.md":"e5219b9f","notes_07-custom-types.md":"44eebba7","syllabus.md":"dae1514f","notes_05-do-while-for.md":"4d7de371","notes_05-loop-design.md":"3d25c934","notes_05-random-numbers.md":"27456932","notes_06-function-overloading-default-parameters.md":"56bf4225","notes_06-recursion.md":"6cb84aa2","notes_07-enums.md":"78b6a90e"}
